giscemultitools/__init__.py
giscemultitools/main.py
giscemultitools/githubutils/__init__.py
giscemultitools/githubutils/changelog_v2.py
giscemultitools/githubutils/objects.py
giscemultitools/githubutils/utils.py
giscemultitools/githubutils/scripts/__init__.py
giscemultitools/githubutils/scripts/github_cli.py
giscemultitools/slackutils/__init__.py
giscemultitools/slackutils/utils.py
giscemultitools/slackutils/scripts/__init__.py
giscemultitools/slackutils/scripts/slack_cli.py
tests/__init__.py
tests/test_github_cli.py
tests/test_githubutils.py
tests/test_slackutils.py
giscemultitools-1.9.3.dist-info/METADATA
giscemultitools-1.9.3.dist-info/WHEEL
giscemultitools-1.9.3.dist-info/entry_points.txt
giscemultitools-1.9.3.dist-info/top_level.txt
giscemultitools-1.9.3.dist-info/RECORD
