Metadata-Version: 2.4
Name: giscemultitools
Version: 1.9.3
Summary: Llibreria d'utilitats
Home-page: http://www.gisce.net
Author: GISCE
Author-email: devel@gisce.net
License: General Public Licence 2
Provides: giscemultitools
Requires-Dist: requests
Requires-Dist: click
Dynamic: author
Dynamic: author-email
Dynamic: description
Dynamic: home-page
Dynamic: license
Dynamic: provides
Dynamic: requires-dist
Dynamic: summary
